histdatacom/__init__.py
histdatacom/__main__.py
histdatacom/api.py
histdatacom/cli.py
histdatacom/concurrency.py
histdatacom/config.py
histdatacom/csvs.py
histdatacom/exceptions.py
histdatacom/fx_enums.py
histdatacom/histdata_com.py
histdatacom/influx.py
histdatacom/options.py
histdatacom/records.py
histdatacom/utils.py
histdatacom/scraper/__init__.py
histdatacom/scraper/repo.py
histdatacom/scraper/scraper.py
histdatacom/scraper/urls.py
histdatacom-0.78.4.dist-info/LICENSE
histdatacom-0.78.4.dist-info/METADATA
histdatacom-0.78.4.dist-info/WHEEL
histdatacom-0.78.4.dist-info/entry_points.txt
histdatacom-0.78.4.dist-info/top_level.txt
histdatacom-0.78.4.dist-info/RECORD
