Metadata-Version: 2.1
Name: histdatacom
Version: 0.78.4
Summary: A Multi-threaded/Multi-Process command-line utility and python package that downloads currency exchange rates from Histdata.com. Imports to InfluxDB. Can be used in Jupyter Notebooks.
Home-page: https://github.com/dmidlo/histdata.com-tools
Author: David Midlo
Author-email: dmidlo@gmail.com
License: MIT License
Project-URL: Bug Tracker, https://github.com/dmidlo/histdata.com-tools/issues
Keywords: finance,data,datascience,HistData.com,scraper,influxdb,currency exchange,forex,fx,etl
Classifier: Development Status :: 4 - Beta
Classifier: Intended Audience :: Science/Research
Classifier: License :: OSI Approved :: MIT License
Classifier: Environment :: MacOS X
Classifier: Operating System :: MacOS
Classifier: Environment :: Win32 (MS Windows)
Classifier: Operating System :: Microsoft :: Windows
Classifier: Programming Language :: Python :: 3.10
Classifier: Topic :: Software Development :: Libraries :: Python Modules
Classifier: Framework :: Jupyter
Classifier: Topic :: Terminals
Requires-Python: >=3.10.0
License-File: LICENSE
Requires-Dist: influxdb-client
Requires-Dist: rich
Requires-Dist: requests
Requires-Dist: beautifulsoup4
Requires-Dist: pyyaml
Requires-Dist: rx
Requires-Dist: argparse
Requires-Dist: pytz
Requires-Dist: certifi
Provides-Extra: arrow
Requires-Dist: pyarrow ; extra == 'arrow'
Provides-Extra: dev
Requires-Dist: pyarrow ; extra == 'dev'
Requires-Dist: pandas ; extra == 'dev'
Requires-Dist: jupyter ; extra == 'dev'
Requires-Dist: ipywidgets ; extra == 'dev'
Requires-Dist: pytest ; extra == 'dev'
Requires-Dist: mypy ; extra == 'dev'
Requires-Dist: keyring ; extra == 'dev'
Requires-Dist: sh ; extra == 'dev'
Requires-Dist: flake8 ; extra == 'dev'
Requires-Dist: black ; extra == 'dev'
Requires-Dist: flake8-black ; extra == 'dev'
Requires-Dist: coverage ; extra == 'dev'
Requires-Dist: pytest-cov ; extra == 'dev'
Requires-Dist: pylint ; extra == 'dev'
Requires-Dist: bandit ; extra == 'dev'
Requires-Dist: flake8-bandit ; extra == 'dev'
Requires-Dist: flake8-comprehensions ; extra == 'dev'
Requires-Dist: flake8-class-attributes-order ; extra == 'dev'
Requires-Dist: flake8-bugbear ; extra == 'dev'
Requires-Dist: pyflakes ; extra == 'dev'
Requires-Dist: pre-commit ; extra == 'dev'
Requires-Dist: types-setuptools ; extra == 'dev'
Requires-Dist: pandas-stubs ; extra == 'dev'
Requires-Dist: types-beautifulsoup4 ; extra == 'dev'
Requires-Dist: wemake-python-styleguide ; extra == 'dev'
Requires-Dist: flake8-simplify ; extra == 'dev'
Requires-Dist: flake8-pie ; extra == 'dev'
Requires-Dist: flake8-use-pathlib ; extra == 'dev'
Requires-Dist: flake8-use-fstring ; extra == 'dev'
Requires-Dist: flake8-print ; extra == 'dev'
Requires-Dist: flake8-no-implicit-concat ; extra == 'dev'
Requires-Dist: pycodestyle ; extra == 'dev'
Requires-Dist: flake8-pytest-style ; extra == 'dev'
Requires-Dist: Flake8-AAA ; extra == 'dev'
Requires-Dist: flake8-spellcheck ; extra == 'dev'
Requires-Dist: flake8-docstring-checker ; extra == 'dev'
Requires-Dist: flake8-docstrings ; extra == 'dev'
Requires-Dist: flake8-coding ; extra == 'dev'
Requires-Dist: flake8-length ; extra == 'dev'
Requires-Dist: flake8-functions ; extra == 'dev'
Requires-Dist: flake8-expression-complexity ; extra == 'dev'
Requires-Dist: flake8-cognitive-complexity ; extra == 'dev'
Requires-Dist: flake8-annotations-complexity ; extra == 'dev'
Requires-Dist: cohesion ; extra == 'dev'
Requires-Dist: Darglint ; extra == 'dev'
Requires-Dist: tryceratops ; extra == 'dev'
Requires-Dist: radon ; extra == 'dev'
Requires-Dist: pyroma ; extra == 'dev'
Requires-Dist: vulture ; extra == 'dev'
Requires-Dist: flake8-type-checking ; extra == 'dev'
Requires-Dist: isort ; extra == 'dev'
Requires-Dist: sourcery-cli ; extra == 'dev'
Provides-Extra: jupyter
Requires-Dist: jupyter ; extra == 'jupyter'
Requires-Dist: ipywidgets ; extra == 'jupyter'
Provides-Extra: pandas
Requires-Dist: pandas ; extra == 'pandas'
